dgllife/__init__.py
dgllife/libinfo.py
dgllife/data/__init__.py
dgllife/data/alchemy.py
dgllife/data/astrazeneca_chembl_solubility.py
dgllife/data/bace.py
dgllife/data/bbbp.py
dgllife/data/clintox.py
dgllife/data/csv_dataset.py
dgllife/data/esol.py
dgllife/data/freesolv.py
dgllife/data/hiv.py
dgllife/data/jtvae.py
dgllife/data/lipophilicity.py
dgllife/data/muv.py
dgllife/data/pcba.py
dgllife/data/pdbbind.py
dgllife/data/pubchem_aromaticity.py
dgllife/data/sider.py
dgllife/data/smiles_inference.py
dgllife/data/tox21.py
dgllife/data/toxcast.py
dgllife/data/uspto.py
dgllife/model/__init__.py
dgllife/model/gnn/__init__.py
dgllife/model/gnn/attentivefp.py
dgllife/model/gnn/gat.py
dgllife/model/gnn/gatv2.py
dgllife/model/gnn/gcn.py
dgllife/model/gnn/gin.py
dgllife/model/gnn/gnn_ogb.py
dgllife/model/gnn/graphsage.py
dgllife/model/gnn/mgcn.py
dgllife/model/gnn/mpnn.py
dgllife/model/gnn/nf.py
dgllife/model/gnn/pagtn.py
dgllife/model/gnn/schnet.py
dgllife/model/gnn/weave.py
dgllife/model/gnn/wln.py
dgllife/model/model_zoo/__init__.py
dgllife/model/model_zoo/acnn.py
dgllife/model/model_zoo/attentivefp_predictor.py
dgllife/model/model_zoo/dgmg.py
dgllife/model/model_zoo/gat_predictor.py
dgllife/model/model_zoo/gatv2_predictor.py
dgllife/model/model_zoo/gcn_predictor.py
dgllife/model/model_zoo/gin_predictor.py
dgllife/model/model_zoo/gnn_ogb_predictor.py
dgllife/model/model_zoo/hadamard_link_predictor.py
dgllife/model/model_zoo/jtvae.py
dgllife/model/model_zoo/mgcn_predictor.py
dgllife/model/model_zoo/mlp_predictor.py
dgllife/model/model_zoo/mpnn_predictor.py
dgllife/model/model_zoo/nf_predictor.py
dgllife/model/model_zoo/pagtn_predictor.py
dgllife/model/model_zoo/potentialnet.py
dgllife/model/model_zoo/schnet_predictor.py
dgllife/model/model_zoo/weave_predictor.py
dgllife/model/model_zoo/wln_reaction_center.py
dgllife/model/model_zoo/wln_reaction_ranking.py
dgllife/model/pretrain/__init__.py
dgllife/model/pretrain/generative_models.py
dgllife-0.3.1.dist-info/METADATA
dgllife-0.3.1.dist-info/WHEEL
dgllife-0.3.1.dist-info/top_level.txt
dgllife-0.3.1.dist-info/RECORD
