Metadata-Version: 2.1
Name: dgllife
Version: 0.3.1
Summary: DGL-based package for Life Science
Home-page: https://github.com/awslabs/dgl-lifesci
Maintainer: DGL Team
License: APACHE
Keywords: pytorch,dgl,graph-neural-networks,life-science,drug-discovery
Classifier: Development Status :: 3 - Alpha
Classifier: Programming Language :: Python :: 3
Classifier: License :: OSI Approved :: Apache Software License
Requires-Dist: scikit-learn (>=0.22.2)
Requires-Dist: pandas
Requires-Dist: requests (>=2.22.0)
Requires-Dist: tqdm
Requires-Dist: numpy (>=1.14.0)
Requires-Dist: scipy (>=1.1.0)
Requires-Dist: networkx (>=2.1)
Requires-Dist: hyperopt
Requires-Dist: joblib
